Utils.py
stringutil/FormatString.py
stringutil/__init__.py
tests/__init__.py
timeutil/TimeFormat.py
timeutil/__init__.py
cn_hn_czutils-1.0.1.dist-info/LICENSE.txt
cn_hn_czutils-1.0.1.dist-info/METADATA
cn_hn_czutils-1.0.1.dist-info/WHEEL
cn_hn_czutils-1.0.1.dist-info/top_level.txt
cn_hn_czutils-1.0.1.dist-info/RECORD
