Metadata-Version: 2.1
Name: cn_hn_czutils
Version: 1.0.1
Summary: CZ-Utils工具库
Home-page: http://www.sheungee.com.cn/
Author: caozz
Author-email: caozz1119@163.com
License-File: LICENSE.txt
